multimeter/__init__.py
multimeter/measure.py
multimeter/measurement.py
multimeter/metric.py
multimeter/multimeter.py
multimeter/probe.py
multimeter/result.py
multimeter/subject.py
multimeter/visualization.py
multimeter/storages/__init__.py
multimeter/storages/base.py
multimeter/storages/dummy.py
multimeter/storages/file.py
multimeter/storages/influx.py
multimeter/visualization/docker-compose.yml
multimeter/visualization/grafana/dashboards/multimeter.json
multimeter/visualization/grafana/provisioning/dashboards/providers.yml
multimeter/visualization/grafana/provisioning/datasources/influxdb.yml
multimeter/visualization/influxdb/example.line
multimeter-0.1.dist-info/entry_points.txt
multimeter-0.1.dist-info/LICENSE
multimeter-0.1.dist-info/WHEEL
multimeter-0.1.dist-info/METADATA
multimeter-0.1.dist-info/RECORD
