Metadata-Version: 2.1
Name: multimeter
Version: 0.1
Summary: Measure resource usage of your python code
Keywords: machine learning,process,profile,measure,cpu,memory,io,network,resources,track,metrics,time series
Author-email: Christoph Emonds <chris+git@kant.ai>
Requires-Python: >=3.6
Classifier: Intended Audience :: Developers
Classifier: License :: OSI Approved :: MIT License
Classifier: Programming Language :: Python :: 3
Classifier: Topic :: Software Development :: Libraries :: Python Modules
Requires-Dist: tox ; extra == "docs"
Requires-Dist: influxdb-client ; extra == "influxdb"
Requires-Dist: flit ; extra == "release"
Requires-Dist: tox ; extra == "test"
Project-URL: Documentation, https://docs.kant.ai/multimeter/latest/
Project-URL: Source, https://gitlab.com/kantai/multimeter/
Provides-Extra: docs
Provides-Extra: influxdb
Provides-Extra: release
Provides-Extra: test
